wq.core-1.2.0-py3.5-nspkg.pth
wq/core/__init__.py
wq/core/decorators.py
wq/core/info.py
wq.core-1.2.0.dist-info/LICENSE
wq.core-1.2.0.dist-info/METADATA
wq.core-1.2.0.dist-info/WHEEL
wq.core-1.2.0.dist-info/entry_points.txt
wq.core-1.2.0.dist-info/namespace_packages.txt
wq.core-1.2.0.dist-info/top_level.txt
wq.core-1.2.0.dist-info/RECORD
